dbt_rpc_client/__init__.py
dbt_rpc_client/client.py
dbt_rpc_client/version.py
dbt_rpc_client-0.1.0.dist-info/LICENSE
dbt_rpc_client-0.1.0.dist-info/METADATA
dbt_rpc_client-0.1.0.dist-info/WHEEL
dbt_rpc_client-0.1.0.dist-info/top_level.txt
dbt_rpc_client-0.1.0.dist-info/RECORD
