Metadata-Version: 2.1
Name: dbt-rpc-client
Version: 0.1.0
Summary: A python SDK for the dbt RPC server.
Home-page: https://github.com/goodeggs/dbt-rpc-client
Author: David Wallace
Author-email: david.wallace@goodeggs.com
License: MIT
Keywords: dbt python rpc
Platform: UNKNOWN
Classifier: License :: OSI Approved :: MIT License
Classifier: Development Status :: 5 - Production/Stable
Classifier: Natural Language :: English
Classifier: Topic :: Software Development
Classifier: Intended Audience :: Developers
Classifier: Operating System :: OS Independent
Classifier: Programming Language :: Python :: 3 :: Only
Classifier: Programming Language :: Python :: 3.6
Classifier: Programming Language :: Python :: 3.7
Classifier: Programming Language :: Python :: 3.8
Requires-Python: >=3.6
Requires-Dist: requests (>=2.22.0)
Requires-Dist: attrs (>=19.3.0)
